README.rst
setup.cfg
setup.py
aws_tools/__init__.py
aws_tools/dynamodb_handler.py
aws_tools/lambda_handler.py
aws_tools/s3_handler.py
aws_tools/ses_handler.py
client_tools/__init__.py
door43_tools/__init__.py
door43_tools/bible_books.py
door43_tools/language_handler.py
door43_tools/manifest_handler.py
door43_tools/obs_data.py
door43_tools/obs_handler.py
door43_tools/preprocessors.py
door43_tools/templaters.py
general_tools/__init__.py
general_tools/file_utils.py
general_tools/print_utils.py
general_tools/smartquotes.py
general_tools/url_utils.py
gogs_tools/__init__.py
gogs_tools/gogs_handler.py
tx_shared_tools.egg-info/PKG-INFO
tx_shared_tools.egg-info/SOURCES.txt
tx_shared_tools.egg-info/dependency_links.txt
tx_shared_tools.egg-info/requires.txt
tx_shared_tools.egg-info/top_level.txt