Metadata-Version: 1.0
Name: tx-shared-tools
Version: 0.1.82
Summary: A collection of useful scripts abd classes for tX
Home-page: https://github.org/unfoldingWord-dev/tx-shared-tools
Author: unfoldingWord
Author-email: info@unfoldingword.org
License: MIT
Keywords: unfoldingWord,tx,tools
Platform: UNKNOWN
